Pyjsondb/__init__.py
Pyjsondb/json_ky_db.py
JsonKyDbData-1.0.2.dist-info/METADATA
JsonKyDbData-1.0.2.dist-info/WHEEL
JsonKyDbData-1.0.2.dist-info/top_level.txt
JsonKyDbData-1.0.2.dist-info/RECORD
