Metadata-Version: 2.1
Name: JsonKyDbData
Version: 1.0.2
Summary: Store JSON data to a file!
Author: hxk
Author-email: xiaokang.he@foxmail.com
